quanmodule/__init__.py
quanmodule/add.py
quanmodule/subtract.py
quanmodule/extras/__init__.py
quanmodule/extras/divide.py
quanmodule/extras/multiply.py
quanmodule-0.0.5.dist-info/METADATA
quanmodule-0.0.5.dist-info/WHEEL
quanmodule-0.0.5.dist-info/top_level.txt
quanmodule-0.0.5.dist-info/RECORD
