Metadata-Version: 2.1
Name: quanmodule
Version: 0.0.5
Summary: My first Python package
Home-page: UNKNOWN
Author: Quan Nham
Author-email: beast@yeast.com
License: UNKNOWN
Keywords: Quan,python,speedrun
Platform: UNKNOWN
Classifier: Programming Language :: Python :: 3
Classifier: Operating System :: MacOS :: MacOS X
